saika/__init__.py
saika/app.py
saika/common.py
saika/const.py
saika/context.py
saika/cors.py
saika/enums.py
saika/environ.py
saika/hard_code.py
saika/helper.py
saika/meta_table.py
saika/workers.py
saika/cli/__init__.py
saika/cli/saika/__init__.py
saika/cli/saika/cli.py
saika/cli/saika/docgen.py
saika/cli/saika/make.py
saika/config/__init__.py
saika/config/base.py
saika/config/flask.py
saika/config/free.py
saika/config/provider/__init__.py
saika/config/provider/file.py
saika/config/provider/provider.py
saika/controller/__init__.py
saika/controller/api.py
saika/controller/base.py
saika/controller/blueprint.py
saika/controller/cli.py
saika/controller/view.py
saika/controller/web.py
saika/database/__init__.py
saika/database/config/__init__.py
saika/database/config/connect.py
saika/database/config/database.py
saika/database/config/file.py
saika/decorator/__init__.py
saika/decorator/config.py
saika/decorator/context.py
saika/decorator/controller.py
saika/decorator/database.py
saika/decorator/doc.py
saika/decorator/form.py
saika/decorator/manager.py
saika/decorator/request.py
saika/exception/__init__.py
saika/exception/api.py
saika/exception/exception.py
saika/form/__init__.py
saika/form/fields.py
saika/form/forms.py
saika/form/process.py
saika/server/__init__.py
saika/server/base.py
saika/server/gevent.py
saika/server/gunicorn.py
saika/service/__init__.py
saika/service/forms.py
saika/service/operators.py
saika/socket/__init__.py
saika/socket/controller.py
saika/socket/event.py
saika/socket_io/__init__.py
saika/socket_io/controller.py
saika/socket_io/socketio.py
Saika-0.3.5.dist-info/LICENSE.txt
Saika-0.3.5.dist-info/METADATA
Saika-0.3.5.dist-info/WHEEL
Saika-0.3.5.dist-info/top_level.txt
Saika-0.3.5.dist-info/RECORD
